Workbook

Sheet Index
A1: 티엘비 투자심사 모델
A2: tools/build_excel.py가 model.html에서 생성. 직접 고치지 말 것 — 다음 빌드에 덮인다.
A4: 시트 | B4: 내용
A5: Index | B5: 이 시트
A6: Control | B6: 모델 개요·전역 설정
A7: Assumptions | B7: 가정변수 일람과 근거
A8: Model | B8: 계정 트리 × 연도. 수식이 살아있는 본체
A9: Formula Audit | B9: 모델 원식 ↔ 셀 수식 대조
A10: Structure | B10: 트리 구조·깊이·행 배치
A11: Checks | B11: 부모 = 자식 합 정합 검증
A12: Metadata | B12: 빌드 정보
A14: 셀 색 규약
A15: 파랑 글자 | B15: 하드코딩 입력값 — 여기만 고친다
A16: 검정 글자 | B16: 수식
A17: 회색 배경 | B17: 실적(Historical) 구간 — 공시 확정값

Sheet Control
A1: 컨트롤
A2: 가정을 바꾸려면 Assumptions 시트가 아니라 Model 시트의 파랑 셀을 고친다. Model이 계산의 단일 출처다.
A4: 모델 | B4: 티엘비 투자심사 모델
A5: 통화 단위 | B5: 억원
A6: 범위 | B6: 출하량×단가 → 영업이익 → 밸류에이션
A7: 실적 연도 수 (HIST_N) | B7: 5
A8: 추정 연도 수 | B8: 5
A9: 첫 연도 | B9: 2021
A10: 마지막 연도 | B10: 2030

Sheet Assumptions
A1: 가정변수 일람
A2: 파랑 = 하드코딩 입력값. 근거 열의 대괄호 태그가 객관/주관 구분이다.
D3: 실적 | E3: 실적 | F3: 실적 | G3: 실적 | H3: 실적 | I3: 추정 | J3: 추정 | K3: 추정 | L3: 추정 | M3: 추정
A4: 계정 | B4: 노드 id | C4: 단위 | D4: 2021A | E4: 2022A | F4: 2023A | G4: 2024A | H4: 2025A | I4: 2026E | J4: 2027E | K4: 2028E | L4: 2029E | M4: 2030E | N4: 근거
A5: 목표 EV/EBITDA | B5: target_ev_ebitda | C5: 배 | D5: 12 | E5: 12 | F5: 12 | G5: 12 | H5: 12 | I5: 12 | J5: 12 | K5: 12 | L5: 12 | M5: 12 | N5: [주관·시나리오] 12배. 이 모델에서 가장 강력한 단일 가정이다. 국내 기판 피어의 2026 컨센서스가 14.1~21.3배이고 티엘비 자신이 15.3배이나, 그 배수들은 **사이클 상단에서 형성된 값**이다. 2023~2024년 이 회사의 영업이익률은 1.8%·1.9%였고 그때 배수는 의미를 갖지 못했다. 사이클 중립 EBITDA에 적용할 배수로 12배를 택했다 — 성숙 부품사(3.5~6.2배)보다 확실히 높되 현재 피어 하단(14.1배)보다 낮은 자리다.
A6: 순이익 실적 마스크 | B6: ni_hist | D6: 1 | E6: 1 | F6: 1 | G6: 1 | H6: 1 | I6: 0 | J6: 0 | K6: 0 | L6: 0 | M6: 0 | N6: [객관] 실적 연도 표시(1). 순이익은 적자 연도가 있어 "실적 > 0" 관용구를 쓸 수 없다 — LGD·삼성전자 DS에서 확립한 hist 마스크 패턴.
A7: 순이익 실적 | B7: ni_actual | C7: 억원 | D7: 124.11147 | E7: 305.55635 | F7: 25.146933 | G7: 36.178322 | H7: 190.49051 | I7: 0 | J7: 0 | K7: 0 | L7: 0 | M7: 0 | N7: [객관] 연결 지배주주 순이익 확정값 (사업보고서 연결포괄손익계산서).
A8: 영업외손익 | B8: nonop | C8: 억원 | D8: 15.006323 | E8: -2.3091369 | F8: 2.2124808 | G8: 15.431673 | H8: -15.850519 | I8: 0 | J8: 0 | K8: 0 | L8: 0 | M8: 0 | N8: [주관 추정 · 실적은 공시값] 영업외손익 = 세전이익 − 영업이익. 실적 +15/−2/+2/+15/−16억 등락 — 규모가 작아 0 고정.
A9: 실효세율 | B9: tax_rate | C9: % | D9: 0 | E9: 0 | F9: 0 | G9: 0 | H9: 0 | I9: 0.22 | J9: 0.22 | K9: 0.22 | L9: 0.22 | M9: 0.22 | N9: [주관] 실효세율. 실적 16.6/20.1/23.2/26.6/22.3% — 22%.
A10: 지배지분 비율 | B10: ctrl_ratio | C10: % | D10: 0 | E10: 0 | F10: 0 | G10: 0 | H10: 0 | I10: 1 | J10: 1 | K10: 1 | L10: 1 | M10: 1 | N10: [주관] 지배지분 비율. 비지배 몫이 미미(음수) — 100%.
A11: 상장주식수 | B11: shares | C11: 백만주 | D11: 23.70126 | E11: 23.70126 | F11: 23.70126 | G11: 23.70126 | H11: 23.70126 | I11: 23.70126 | J11: 23.70126 | K11: 23.70126 | L11: 23.70126 | M11: 23.70126 | N11: [객관] 상장주식수 23,701,260주(2026 무상증자 후) 고정. **공시 EPS·DPS는 증자 전 주식수 기준**이라 실적 연도의 주당 값과 기준이 다르다 — 현재가와 비교하는 용도로는 현재 주식수가 맞다.
A12: DPS 실적 | B12: dps_a | C12: 원 | D12: 250 | E12: 300 | F12: 200 | G12: 200 | H12: 450 | I12: 0 | J12: 0 | K12: 0 | L12: 0 | M12: 0 | N12: [객관] 주당 현금배당(당시 주식수 기준). 실적 250/300/200/200/450원.
A13: 배당성향 | B13: payout | C13: % | D13: 0 | E13: 0 | F13: 0 | G13: 0 | H13: 0 | I13: 0.23 | J13: 0.23 | K13: 0.23 | L13: 0.23 | M13: 0.23 | N13: [주관] 배당성향. 실적 9.9/9.7/77.9/53.8/23.0% — 이익 정상 연도 기준 **23%**.
A14: 감가상각비 실적 | B14: dep_actual | C14: 억원 | D14: 35.71458 | E14: 45.83276 | F14: 53.90911 | G14: 59.76686 | H14: 75.01629 | I14: 0 | J14: 0 | K14: 0 | L14: 0 | M14: 0 | N14: [객관] 네 개 사업보고서의 당기/전기가 연쇄적으로 일치해 교차검증됐다.
A15: 감가상각 증가율 | B15: dep_g | C15: % | D15: 0 | E15: 0 | F15: 0 | G15: 0 | H15: 0 | I15: 0.35 | J15: 0.25 | K15: 0.15 | L15: 0.1 | M15: 0.08 | N15: [주관] 2025년 CAPEX가 368.8억으로 감가상각비(75.0억)의 **4.9배**다. 증설이 진행 중이라는 뜻이고, 그 투자분이 2026~2027년에 상각으로 들어온다. 실적 4년 연평균 +20.4%에서 2026년을 +35%로 올린 근거가 이것이다. 생산능력 가정과 방향이 일치해야 한다 — 능력을 늘리면서 상각이 늘지 않는 모델은 성립하지 않는다.
A16: 기타비용 실적 | B16: other_actual | C16: 억원 | D16: 1611.4808 | E16: 1785.0044 | F16: 1628.7082 | G16: 1706.6666 | H16: 2250.3347 | I16: 0 | J16: 0 | K16: 0 | L16: 0 | M16: 0 | N16: [객관] 확정값에서 역산. 세 항목 모두 공시값이라 결과도 확정이다.
A17: 기타비용률 | B17: other_ratio | C17: % | D17: 0 | E17: 0 | F17: 0 | G17: 0 | H17: 0 | I17: 0.83 | J17: 0.825 | K17: 0.82 | L17: 0.815 | M17: 0.81 | N17: [주관] 매출 대비 기타비용. 실적 90.5 → 80.6 → 95.1 → 94.8 → 87.1%로 **사이클에 따라 15%p나 흔들린다** — 고정비 비중이 높은 장치산업의 특징이다. 2026 상반기 실적(매출 1,640.8억 · 영업이익 234.9억)에서 역산하면 82.9% 수준이라 2026년을 83.0%로 두고 연 0.5%p씩만 개선한다고 봤다. 2022년 저점(80.6%)까지 가는 것은 Bull에서만 가정한다.
A18: 생산능력 | B18: capacity | C18: 천㎡ | D18: 342 | E18: 348 | F18: 348 | G18: 348 | H18: 348 | I18: 360 | J18: 400 | K18: 430 | L18: 450 | M18: 460 | N18: [객관 실적 / 주관 추정] 공시 기준 월 29,000㎡ × 12개월 = 348천㎡로 2022년 이후 **4년째 고정**이다. 이것이 이 모델의 상한선이고, 증설 없이는 물량이 348천㎡를 넘을 수 없다. 추정 구간은 2025년 CAPEX 368.8억(감가상각의 4.9배)을 근거로 늘려 잡았고, 2026-09 증권사 실사(IBK)로 방향이 확인됐다 — 2Q26 베트남 2공장·안산에 매스램 병목 해소 설비 가동, **베트남 신공장 4Q27 가동 예정**(2027 400천㎡ 가정과 정합). 다만 회사가 수치로 공시한 계획은 여전히 없어 이 부분은 판단이다. 민감도 뷰에서 영향도를 확인할 것.
... A21: 순차입금 | B21: net_debt | C21: 억원 | D21: 70.039454 | E21: -52.71278 | F21: 298.34464 | G21: 334.64758 | H21: 617.63878 | I21: 617.63878 | J21: 617.63878 | K21: 617.63878 | L21: 617.63878 | M21: 617.63878 | N21: [객관 실적 / 추정 구간 고정] 차입금(단기+유동성장기+장기) − 현금및현금성자산. 리스부채 제외. 2022년 −52.7억(순현금)에서 2025년 617.6억으로 3년 만에 670억이 늘었다 — 증설 투자를 차입으로 감당한 결과다. 시가총액의 6.3%로 삼성전기·KT&G보다 밸류에이션 민감도가 크다. 추정 구간은 2025년 수준으로 고정했으나, CAPEX가 감가상각의 5배인 국면이라 실제로는 더 늘 가능성이 높다.

Sheet Model
A1: 티엘비 투자심사 모델
A2: 단위 억원 · 실적 5개년 + 추정 5개년
D3: 실적 | E3: 실적 | F3: 실적 | G3: 실적 | H3: 실적 | I3: 추정 | J3: 추정 | K3: 추정 | L3: 추정 | M3: 추정
A4: 계정 | B4: 노드 id | C4: 단위 | D4: 2021A | E4: 2022A | F4: 2023A | G4: 2024A | H4: 2025A | I4: 2026E | J4: 2027E | K4: 2028E | L4: 2029E | M4: 2030E
A5: 적정 시가총액 | B5: root | C5: 억원 | D5: =(D6-D33) | E5: =(E6-E33) | F5: =(F6-F33) | G5: =(G6-G33) | H5: =(H6-H33) | I5: =(I6-I33) | J5: =(J6-J33) | K5: =(K6-K33) | ... M5: =(M6-M33)
A6: 사업가치 (EV) | B6: ev_value | C6: 억원 | D6: =(D8*D7) | E6: =(E8*E7) | F6: =(F8*F7) | G6: =(G8*G7) | H6: =(H8*H7) | I6: =(I8*I7) | J6: =(J8*J7) | K6: =(K8*K7) | ... M6: =(M8*M7)
A7: 목표 EV/EBITDA | B7: target_ev_ebitda | C7: 배 | D7: 12 | E7: 12 | F7: 12 | G7: 12 | H7: 12 | I7: 12 | J7: 12 | K7: 12 | L7: 12 | M7: 12
A8: EBITDA | B8: ebitda | C8: 억원 | D8: =(D9+D22) | E8: =(E9+E22) | F8: =(F9+F22) | G8: =(G9+G22) | H8: =(H9+H22) | I8: =(I9+I22) | J8: =(J9+J22) | K8: =(K9+K22) | ... M8: =(M9+M22)
A9: 영업이익 | B9: op_profit | C9: 억원 | D9: =(D28-D21) | E9: =(E28-E21) | F9: =(F28-F21) | G9: =(G28-G21) | H9: =(H28-H21) | I9: =(I28-I21) | J9: =(J28-J21) | K9: =(K28-K21) | ... M9: =(M28-M21)
A10: 지배주주 순이익 (참고) | B10: net_income | C10: 억원 | D10: =IF((D11>0),D12,(((D9+D13)*(1-D14))*D15)) | E10: =IF((E11>0),E12,(((E9+E13)*(1-E14))*E15)) | F10: =IF((F11>0),F12,(((F9+F13)*(1-F14))*F15)) | G10: =IF((G11>0),G12,(((G9+G13)*(1-G14))*G15)) | H10: =IF((H11>0),H12,(((H9+H13)*(1-H14))*H15)) | I10: =IF((I11>0),I12,(((I9+I13)*(1-I14))*I15)) | J10: =IF((J11>0),J12,(((J9+J13)*(1-J14))*J15)) | K10: =IF((K11>0),K12,(((K9+K13)*(1-K14))*K15)) | ... M10: =IF((M11>0),M12,(((M9+M13)*(1-M14))*M15))
A11: 순이익 실적 마스크 | B11: ni_hist | D11: 1 | E11: 1 | F11: 1 | G11: 1 | H11: 1 | I11: 0 | J11: 0 | K11: 0 | L11: 0 | M11: 0
A12: 순이익 실적 | B12: ni_actual | C12: 억원 | D12: 124.11147 | E12: 305.55635 | F12: 25.146933 | G12: 36.178322 | H12: 190.49051 | I12: 0 | J12: 0 | K12: 0 | L12: 0 | M12: 0
A13: 영업외손익 | B13: nonop | C13: 억원 | D13: 15.006323 | E13: -2.3091369 | F13: 2.2124808 | G13: 15.431673 | H13: -15.850519 | I13: 0 | J13: 0 | K13: 0 | L13: 0 | M13: 0
A14: 실효세율 | B14: tax_rate | C14: % | D14: 0 | E14: 0 | F14: 0 | G14: 0 | H14: 0 | I14: 0.22 | J14: 0.22 | K14: 0.22 | L14: 0.22 | M14: 0.22
A15: 지배지분 비율 | B15: ctrl_ratio | C15: % | D15: 0 | E15: 0 | F15: 0 | G15: 0 | H15: 0 | I15: 1 | J15: 1 | K15: 1 | L15: 1 | M15: 1
A16: EPS (참고) | B16: eps | C16: 원 | D16: =((D10/D17)*100) | E16: =((E10/E17)*100) | F16: =((F10/F17)*100) | G16: =((G10/G17)*100) | H16: =((H10/H17)*100) | I16: =((I10/I17)*100) | J16: =((J10/J17)*100) | K16: =((K10/K17)*100) | ... M16: =((M10/M17)*100)
A17: 상장주식수 | B17: shares | C17: 백만주 | D17: 23.70126 | E17: 23.70126 | F17: 23.70126 | G17: 23.70126 | H17: 23.70126 | I17: 23.70126 | J17: 23.70126 | K17: 23.70126 | L17: 23.70126 | M17: 23.70126
A18: DPS (참고) | B18: dps | C18: 원 | D18: =IF((D11>0),D19,(D16*D20)) | E18: =IF((E11>0),E19,(E16*E20)) | F18: =IF((F11>0),F19,(F16*F20)) | G18: =IF((G11>0),G19,(G16*G20)) | H18: =IF((H11>0),H19,(H16*H20)) | I18: =IF((I11>0),I19,(I16*I20)) | J18: =IF((J11>0),J19,(J16*J20)) | K18: =IF((K11>0),K19,(K16*K20)) | ... M18: =IF((M11>0),M19,(M16*M20))
A19: DPS 실적 | B19: dps_a | C19: 원 | D19: 250 | E19: 300 | F19: 200 | G19: 200 | H19: 450 | I19: 0 | J19: 0 | K19: 0 | L19: 0 | M19: 0
A20: 배당성향 | B20: payout | C20: % | D20: 0 | E20: 0 | F20: 0 | G20: 0 | H20: 0 | I20: 0.23 | J20: 0.23 | K20: 0.23 | L20: 0.23 | M20: 0.23
A21: 총비용 | B21: total_cost | C21: 억원 | D21: =(D22+D25) | E21: =(E22+E25) | F21: =(F22+F25) | G21: =(G22+G25) | H21: =(H22+H25) | I21: =(I22+I25) | J21: =(J22+J25) | K21: =(K22+K25) | ... M21: =(M22+M25)
A22: 감가상각비 | B22: dep_total | C22: 억원 | D22: =IF((D23>0),D23,(0*(1+D24))) | E22: =IF((E23>0),E23,(D22*(1+E24))) | F22: =IF((F23>0),F23,(E22*(1+F24))) | G22: =IF((G23>0),G23,(F22*(1+G24))) | H22: =IF((H23>0),H23,(G22*(1+H24))) | I22: =IF((I23>0),I23,(H22*(1+I24))) | J22: =IF((J23>0),J23,(I22*(1+J24))) | K22: =IF((K23>0),K23,(J22*(1+K24))) | L22: =IF((L23>0),L23,(K22*(1+L24))) | M22: =IF((M23>0),M23,(L22*(1+M24)))
A23: 감가상각비 실적 | B23: dep_actual | C23: 억원 | D23: 35.71458 | E23: 45.83276 | F23: 53.90911 | G23: 59.76686 | H23: 75.01629 | I23: 0 | J23: 0 | K23: 0 | L23: 0 | M23: 0
A24: 감가상각 증가율 | B24: dep_g | C24: % | D24: 0 | E24: 0 | F24: 0 | G24: 0 | H24: 0 | I24: 0.35 | J24: 0.25 | K24: 0.15 | L24: 0.1 | M24: 0.08
A25: 기타비용 | B25: other_cost | C25: 억원 | D25: =IF((D26>0),D26,(D28*D27)) | E25: =IF((E26>0),E26,(E28*E27)) | F25: =IF((F26>0),F26,(F28*F27)) | G25: =IF((G26>0),G26,(G28*G27)) | H25: =IF((H26>0),H26,(H28*H27)) | I25: =IF((I26>0),I26,(I28*I27)) | J25: =IF((J26>0),J26,(J28*J27)) | K25: =IF((K26>0),K26,(K28*K27)) | ... M25: =IF((M26>0),M26,(M28*M27))
A26: 기타비용 실적 | B26: other_actual | C26: 억원 | D26: 1611.4808 | E26: 1785.0044 | F26: 1628.7082 | G26: 1706.6666 | H26: 2250.3347 | I26: 0 | J26: 0 | K26: 0 | L26: 0 | M26: 0
A27: 기타비용률 | B27: other_ratio | C27: % | D27: 0 | E27: 0 | F27: 0 | G27: 0 | H27: 0 | I27: 0.83 | J27: 0.825 | K27: 0.82 | L27: 0.815 | M27: 0.81
A28: 매출 | B28: revenue | C28: 억원 | D28: =(D29*D32) | E28: =(E29*E32) | F28: =(F29*F32) | G28: =(G29*G32) | H28: =(H29*H32) | I28: =(I29*I32) | J28: =(J29*J32) | K28: =(K29*K32) | ... M28: =(M29*M32)
A29: 출하량 | B29: qty | C29: 천㎡ | D29: =(D30*D31) | E29: =(E30*E31) | F29: =(F30*F31) | G29: =(G30*G31) | H29: =(H30*H31) | I29: =(I30*I31) | J29: =(J30*J31) | K29: =(K30*K31) | ... M29: =(M30*M31)
A30: 생산능력 | B30: capacity | C30: 천㎡ | D30: 342 | E30: 348 | F30: 348 | G30: 348 | H30: 348 | I30: 360 | J30: 400 | K30: 430 | L30: 450 | M30: 460
A31: 가동률 | B31: util | C31: % | D31: 0.86094632 | E31: 0.80284278 | F31: 0.6552676 | G31: 0.61346027 | H31: 0.67801442 | I31: 0.717 | J31: 0.74 | K31: 0.75 | L31: 0.77 | M31: 0.78
A32: 단가 | B32: price | C32: 억원/천㎡ | D32: 6.04869 | E32: 7.92973 | F32: 7.51236 | G32: 8.4316 | H32: 10.95566 | I32: 14.15 | J32: 15.57 | K32: 16.04 | L32: 16.36 | M32: 16.69
A33: 순차입금 | B33: net_debt | C33: 억원 | D33: 70.039454 | E33: -52.71278 | F33: 298.34464 | G33: 334.64758 | H33: 617.63878 | I33: 617.63878 | J33: 617.63878 | K33: 617.63878 | L33: 617.63878 | M33: 617.63878

Sheet Formula Audit
A1: 수식 감사
A2: 모델 원식 ↔ Excel 셀 수식 대조. 변환은 엔진의 astToExcel이 담당한다.
A4: 노드 id | B4: 계정 | C4: 행 | D4: 모델 원식 | E4: 첫 추정연도 셀 수식
A5: root | B5: 적정 시가총액 | C5: 5 | D5: ev_value - net_debt | E5: '=(I6-I33)
A6: ev_value | B6: 사업가치 (EV) | C6: 6 | D6: ebitda * target_ev_ebitda | E6: '=(I8*I7)
A7: ebitda | B7: EBITDA | C7: 8 | D7: op_profit + dep_total | E7: '=(I9+I22)
A8: op_profit | B8: 영업이익 | C8: 9 | D8: revenue - total_cost | E8: '=(I28-I21)
A9: net_income | B9: 지배주주 순이익 (참고) | C9: 10 | D9: IF(ni_hist > 0, ni_actual, (op_profit + nonop) * (1 - tax_rate) * ctrl_ratio) | E9: '=IF((I11>0),I12,(((I9+I13)*(1-I14))*I15))
A10: eps | B10: EPS (참고) | C10: 16 | D10: net_income / shares * 100 | E10: '=((I10/I17)*100)
A11: dps | B11: DPS (참고) | C11: 18 | D11: IF(ni_hist > 0, dps_a, eps * payout) | E11: '=IF((I11>0),I19,(I16*I20))
A12: total_cost | B12: 총비용 | C12: 21 | D12: dep_total + other_cost | E12: '=(I22+I25)
A13: dep_total | B13: 감가상각비 | C13: 22 | D13: IF(dep_actual > 0, dep_actual, PREV(dep_total) * (1 + dep_g)) | E13: '=IF((I23>0),I23,(H22*(1+I24)))
A14: other_cost | B14: 기타비용 | C14: 25 | D14: IF(other_actual > 0, other_actual, revenue * other_ratio) | E14: '=IF((I26>0),I26,(I28*I27))
A15: revenue | B15: 매출 | C15: 28 | D15: qty * price | E15: '=(I29*I32)
A16: qty | B16: 출하량 | C16: 29 | D16: capacity * util | E16: '=(I30*I31)

Sheet Structure
A1: 트리 구조
A3: 노드 id | B3: 계정 | C3: 깊이 | D3: 유형 | E3: 합계형 | F3: 행 | G3: 단위
A4: root | B4: 적정 시가총액 | C4: 0 | D4: computed | F4: 5 | G4: 억원
A5: ev_value | B5: 사업가치 (EV) | C5: 1 | D5: computed | F5: 6 | G5: 억원
A6: target_ev_ebitda | B6: 목표 EV/EBITDA | C6: 2 | D6: input | F6: 7 | G6: 배
A7: ebitda | B7: EBITDA | C7: 2 | D7: computed | F7: 8 | G7: 억원
A8: op_profit | B8: 영업이익 | C8: 3 | D8: computed | F8: 9 | G8: 억원
A9: net_income | B9: 지배주주 순이익 (참고) | C9: 4 | D9: computed | F9: 10 | G9: 억원
A10: ni_hist | B10: 순이익 실적 마스크 | C10: 5 | D10: input | F10: 11
A11: ni_actual | B11: 순이익 실적 | C11: 5 | D11: input | F11: 12 | G11: 억원
A12: nonop | B12: 영업외손익 | C12: 5 | D12: input | F12: 13 | G12: 억원
A13: tax_rate | B13: 실효세율 | C13: 5 | D13: input | F13: 14 | G13: %
A14: ctrl_ratio | B14: 지배지분 비율 | C14: 5 | D14: input | F14: 15 | G14: %
A15: eps | B15: EPS (참고) | C15: 5 | D15: computed | F15: 16 | G15: 원
A16: shares | B16: 상장주식수 | C16: 6 | D16: input | F16: 17 | G16: 백만주
A17: dps | B17: DPS (참고) | C17: 6 | D17: computed | F17: 18 | G17: 원
A18: dps_a | B18: DPS 실적 | C18: 7 | D18: input | F18: 19 | G18: 원
A19: payout | B19: 배당성향 | C19: 7 | D19: input | F19: 20 | G19: %
A20: total_cost | B20: 총비용 | C20: 4 | D20: computed | E20: Y | F20: 21 | G20: 억원
A21: dep_total | B21: 감가상각비 | C21: 5 | D21: computed | F21: 22 | G21: 억원
A22: dep_actual | B22: 감가상각비 실적 | C22: 6 | D22: input | F22: 23 | G22: 억원
A23: dep_g | B23: 감가상각 증가율 | C23: 6 | D23: input | F23: 24 | G23: %
A24: other_cost | B24: 기타비용 | C24: 5 | D24: computed | F24: 25 | G24: 억원
A25: other_actual | B25: 기타비용 실적 | C25: 6 | D25: input | F25: 26 | G25: 억원
A26: other_ratio | B26: 기타비용률 | C26: 6 | D26: input | F26: 27 | G26: %
A27: revenue | B27: 매출 | C27: 4 | D27: computed | F27: 28 | G27: 억원
A28: qty | B28: 출하량 | C28: 5 | D28: computed | F28: 29 | G28: 천㎡
A29: capacity | B29: 생산능력 | C29: 6 | D29: input | F29: 30 | G29: 천㎡
A30: util | B30: 가동률 | C30: 6 | D30: input | F30: 31 | G30: %
A31: price | B31: 단가 | C31: 5 | D31: input | F31: 32 | G31: 억원/천㎡
A32: net_debt | B32: 순차입금 | C32: 1 | D32: input | F32: 33 | G32: 억원

Sheet Checks
A1: 검증
A2: 합계형 노드의 부모값과 자식 합의 차이. 전 칸이 0이어야 한다.
D3: 실적 | E3: 실적 | F3: 실적 | G3: 실적 | H3: 실적 | I3: 추정 | J3: 추정 | K3: 추정 | L3: 추정 | M3: 추정
A4: 계정 | B4: 검사 | D4: 2021A | E4: 2022A | F4: 2023A | G4: 2024A | H4: 2025A | I4: 2026E | J4: 2027E | K4: 2028E | L4: 2029E | M4: 2030E
A5: 총비용 | B5: 부모 − 자식합 | D5: =ROUND(Model!D21-(Model!D22+Model!D25),6) | E5: =ROUND(Model!E21-(Model!E22+Model!E25),6) | F5: =ROUND(Model!F21-(Model!F22+Model!F25),6) | G5: =ROUND(Model!G21-(Model!G22+Model!G25),6) | H5: =ROUND(Model!H21-(Model!H22+Model!H25),6) | I5: =ROUND(Model!I21-(Model!I22+Model!I25),6) | J5: =ROUND(Model!J21-(Model!J22+Model!J25),6) | K5: =ROUND(Model!K21-(Model!K22+Model!K25),6) | ... M5: =ROUND(Model!M21-(Model!M22+Model!M25),6)
A7: 합계형 노드 수 | B7: 1

Sheet Metadata
A1: 빌드 정보
A3: 소스 | B3: model.html
A4: 소스 해시 (sha256 앞 16자리) | B4: f15ec97e72813ff5
A5: 빌더 | B5: tools/build_excel.py
A6: 수식 변환 | B6: 엔진 astToExcel (JS) — 파이썬은 배치만 한다
A7: 노드 수 | B7: 29
A8: 입력 노드 수 | B8: 17
A9: 연도 수 | B9: 10
A10: HIST_N | B10: 5
A11: 모델 id | B11: tlb_qp
